qsttoolkit/__init__.py
qsttoolkit/plots.py
qsttoolkit/quantum.py
qsttoolkit/utils.py
qsttoolkit/data/__init__.py
qsttoolkit/data/datasets.py
qsttoolkit/data/measurement.py
qsttoolkit/data/noise.py
qsttoolkit/data/num_state_coeffs.py
qsttoolkit/data/state_batches.py
qsttoolkit/data/states.py
qsttoolkit/tomography/QST.py
qsttoolkit/tomography/__init__.py
qsttoolkit/tomography/loss.py
qsttoolkit/tomography/dlqst/__init__.py
qsttoolkit/tomography/dlqst/CNN_classifier/__init__.py
qsttoolkit/tomography/dlqst/CNN_classifier/architecture.py
qsttoolkit/tomography/dlqst/CNN_classifier/model.py
qsttoolkit/tomography/dlqst/GAN_reconstructor/__init__.py
qsttoolkit/tomography/dlqst/GAN_reconstructor/architecture.py
qsttoolkit/tomography/dlqst/GAN_reconstructor/model.py
qsttoolkit/tomography/dlqst/GAN_reconstructor/train.py
qsttoolkit/tomography/dlqst/multitask_reconstructor/__init__.py
qsttoolkit/tomography/dlqst/multitask_reconstructor/architecture.py
qsttoolkit/tomography/dlqst/multitask_reconstructor/model.py
qsttoolkit/tomography/dlqst/multitask_reconstructor/reconstruction.py
qsttoolkit/tomography/tradqst/__init__.py
qsttoolkit/tomography/tradqst/MLE_reconstructor/__init__.py
qsttoolkit/tomography/tradqst/MLE_reconstructor/model.py
qsttoolkit/tomography/tradqst/MLE_reconstructor/train.py
qsttoolkit-1.2.0.dist-info/licenses/LICENSE
qsttoolkit-1.2.0.dist-info/METADATA
qsttoolkit-1.2.0.dist-info/WHEEL
qsttoolkit-1.2.0.dist-info/top_level.txt
qsttoolkit-1.2.0.dist-info/RECORD
