Metadata-Version: 2.4
Name: qsttoolkit
Version: 1.2.0
Summary: The definitive, open-source package for performing optical quantum state tomography using both traditional (statistical) and novel deep learning-powered methods in Python.
Home-page: https://github.com/georgefitzgerald02/qsttoolkit
Author: George FitzGerald
Author-email: gwfitzg@hotmail.com
License: MIT
Classifier: Programming Language :: Python :: 3
Classifier: License :: OSI Approved :: MIT License
Classifier: Operating System :: OS Independent
License-File: LICENSE
Requires-Dist: numpy==2.0.2
Requires-Dist: scipy==1.14.1
Requires-Dist: pandas==2.2.2
Requires-Dist: matplotlib==3.10.0
Requires-Dist: seaborn==0.13.2
Requires-Dist: qutip==5.1.1
Requires-Dist: scikit-learn==1.6.1
Requires-Dist: tensorflow>=2.18.0
Dynamic: author
Dynamic: author-email
Dynamic: classifier
Dynamic: description
Dynamic: description-content-type
Dynamic: home-page
Dynamic: license
Dynamic: license-file
Dynamic: requires-dist
Dynamic: summary
